youtrack_cli/HELP_STYLE_GUIDE.md
youtrack_cli/__init__.py
youtrack_cli/admin.py
youtrack_cli/articles.py
youtrack_cli/auth.py
youtrack_cli/batch.py
youtrack_cli/boards.py
youtrack_cli/cache.py
youtrack_cli/client.py
youtrack_cli/common.py
youtrack_cli/config.py
youtrack_cli/console.py
youtrack_cli/custom_field_manager.py
youtrack_cli/custom_field_types.py
youtrack_cli/error_formatting.py
youtrack_cli/exceptions.py
youtrack_cli/field_selection.py
youtrack_cli/help_system.py
youtrack_cli/issues.py
youtrack_cli/logging.py
youtrack_cli/main.py
youtrack_cli/models.py
youtrack_cli/pagination.py
youtrack_cli/panels.py
youtrack_cli/performance.py
youtrack_cli/performance_benchmark.py
youtrack_cli/progress.py
youtrack_cli/projects.py
youtrack_cli/reports.py
youtrack_cli/security.py
youtrack_cli/themes.py
youtrack_cli/time.py
youtrack_cli/trees.py
youtrack_cli/users.py
youtrack_cli/utils.py
youtrack_cli/validation.py
youtrack_cli/cli_utils/__init__.py
youtrack_cli/cli_utils/aliases.py
youtrack_cli/cli_utils/validation.py
youtrack_cli/commands/__init__.py
youtrack_cli/commands/articles.py
youtrack_cli/commands/boards.py
youtrack_cli/commands/common.py
youtrack_cli/commands/issues.py
youtrack_cli/commands/projects.py
youtrack_cli/commands/time_tracking.py
youtrack_cli/commands/tutorial.py
youtrack_cli/commands/users.py
youtrack_cli/managers/__init__.py
youtrack_cli/managers/issues.py
youtrack_cli/managers/projects.py
youtrack_cli/managers/users.py
youtrack_cli/services/__init__.py
youtrack_cli/services/base.py
youtrack_cli/services/field_cache.py
youtrack_cli/services/issues.py
youtrack_cli/services/projects.py
youtrack_cli/services/users.py
youtrack_cli/tutorial/__init__.py
youtrack_cli/tutorial/core.py
youtrack_cli/tutorial/docker_utils.py
youtrack_cli/tutorial/executor.py
youtrack_cli/tutorial/modules.py
youtrack_cli/tutorial/progress.py
youtrack_cli/py.typed
youtrack_cli-0.21.0.dist-info/METADATA
youtrack_cli-0.21.0.dist-info/WHEEL
youtrack_cli-0.21.0.dist-info/entry_points.txt
youtrack_cli-0.21.0.dist-info/RECORD
