Metadata-Version: 2.4
Name: youtrack-cli
Version: 0.21.0
Summary: YouTrack CLI - Command line interface for JetBrains YouTrack issue tracking system
Project-URL: Homepage, https://github.com/ryancheley/yt-cli
Project-URL: Documentation, https://yt-cli.readthedocs.io/
Project-URL: Repository, https://github.com/ryancheley/yt-cli.git
Project-URL: Issues, https://github.com/ryancheley/yt-cli/issues
Project-URL: Changelog, https://github.com/ryancheley/yt-cli/blob/main/CHANGELOG.md
Author-email: Ryan Cheley <rcheley@gmail.com>
License: MIT
Keywords: cli,issue-tracking,jetbrains,project-management,youtrack
Classifier: Development Status :: 4 - Beta
Classifier: Environment :: Console
Classifier: Intended Audience :: Developers
Classifier: License :: OSI Approved :: MIT License
Classifier: Operating System :: OS Independent
Classifier: Programming Language :: Python :: 3
Classifier: Programming Language :: Python :: 3.9
Classifier: Programming Language :: Python :: 3.10
Classifier: Programming Language :: Python :: 3.11
Classifier: Programming Language :: Python :: 3.12
Classifier: Programming Language :: Python :: 3.13
Classifier: Topic :: Software Development :: Bug Tracking
Classifier: Topic :: Software Development :: Libraries :: Python Modules
Classifier: Topic :: Utilities
Requires-Python: <3.14,>=3.9
Requires-Dist: click>=8.0.0
Requires-Dist: cryptography>=41.0.0
Requires-Dist: docker>=7.0.0
Requires-Dist: httpx>=0.24.0
Requires-Dist: keyring>=25.0.0
Requires-Dist: pydantic-settings>=2.0.0
Requires-Dist: pydantic>=2.0.0
Requires-Dist: python-dotenv>=1.0.0
Requires-Dist: rich>=13.0.0
Requires-Dist: selenium>=4.34.2
Requires-Dist: structlog>=25.4.0
Requires-Dist: textual>=0.40.0
Requires-Dist: tomli>=1.2.0; python_version < '3.11'
Requires-Dist: ty>=0.0.1a14
